<?xml version="1.0" encoding="UTF-8"?>
<TextureAtlas imagePath="ExtremeDemon_Assets.png">
<!--
Created with Free texture packer v0.6.7 http://free-tex-packer.com
-->
  <SubTexture name="ExtremeDemonAnimation0000" x="0" y="0"  width="179" height="170" frameX="0" frameY="-246" frameWidth="407" frameHeight="418"/>
  <SubTexture name="ExtremeDemonAnimation0001" x="0" y="0"  width="179" height="170" frameX="0" frameY="-246" frameWidth="407" frameHeight="418"/>
  <SubTexture name="ExtremeDemonAnimation0002" x="0" y="0"  width="179" height="170" frameX="0" frameY="-246" frameWidth="407" frameHeight="418"/>
  <SubTexture name="ExtremeDemonAnimation0003" x="0" y="0"  width="179" height="170" frameX="0" frameY="-246" frameWidth="407" frameHeight="418"/>
  <SubTexture name="ExtremeDemonAnimation0004" x="0" y="0"  width="179" height="170" frameX="0" frameY="-246" frameWidth="407" frameHeight="418"/>
  <SubTexture name="ExtremeDemonAnimation0005" x="0" y="0"  width="179" height="170" frameX="0" frameY="-246" frameWidth="407" frameHeight="418"/>
  <SubTexture name="ExtremeDemonAnimation0006" x="0" y="0"  width="179" height="170" frameX="0" frameY="-246" frameWidth="407" frameHeight="418"/>
  <SubTexture name="ExtremeDemonAnimation0007" x="0" y="0"  width="179" height="170" frameX="0" frameY="-246" frameWidth="407" frameHeight="418"/>
  <SubTexture name="ExtremeDemonAnimation0008" x="0" y="0"  width="179" height="170" frameX="0" frameY="-246" frameWidth="407" frameHeight="418"/>
  <SubTexture name="ExtremeDemonAnimation0009" x="0" y="0"  width="179" height="170" frameX="0" frameY="-246" frameWidth="407" frameHeight="418"/>
  <SubTexture name="ExtremeDemonAnimation0010" x="0" y="0"  width="179" height="170" frameX="0" frameY="-246" frameWidth="407" frameHeight="418"/>
  <SubTexture name="ExtremeDemonAnimation0011" x="0" y="0"  width="179" height="170" frameX="0" frameY="-246" frameWidth="407" frameHeight="418"/>
  <SubTexture name="ExtremeDemonAnimation0012" x="0" y="0"  width="179" height="170" frameX="0" frameY="-246" frameWidth="407" frameHeight="418"/>
  <SubTexture name="ExtremeDemonAnimation0013" x="0" y="0"  width="179" height="170" frameX="0" frameY="-246" frameWidth="407" frameHeight="418"/>
  <SubTexture name="ExtremeDemonAnimation0014" x="0" y="0"  width="179" height="170" frameX="0" frameY="-246" frameWidth="407" frameHeight="418"/>
  <SubTexture name="ExtremeDemonAnimation0015" x="0" y="0"  width="179" height="170" frameX="0" frameY="-246" frameWidth="407" frameHeight="418"/>
  <SubTexture name="ExtremeDemonAnimation0016" x="0" y="0"  width="179" height="170" frameX="0" frameY="-246" frameWidth="407" frameHeight="418"/>
  <SubTexture name="ExtremeDemonAnimation0017" x="0" y="0"  width="179" height="170" frameX="0" frameY="-246" frameWidth="407" frameHeight="418"/>
  <SubTexture name="ExtremeDemonAnimation0018" x="0" y="0"  width="179" height="170" frameX="0" frameY="-246" frameWidth="407" frameHeight="418"/>
  <SubTexture name="ExtremeDemonAnimation0019" x="0" y="0"  width="179" height="170" frameX="0" frameY="-246" frameWidth="407" frameHeight="418"/>
  <SubTexture name="ExtremeDemonAnimation0020" x="0" y="0"  width="179" height="170" frameX="0" frameY="-246" frameWidth="407" frameHeight="418"/>
  <SubTexture name="ExtremeDemonAnimation0021" x="0" y="0"  width="179" height="170" frameX="0" frameY="-246" frameWidth="407" frameHeight="418"/>
  <SubTexture name="ExtremeDemonAnimation0022" x="0" y="0"  width="179" height="170" frameX="0" frameY="-246" frameWidth="407" frameHeight="418"/>
  <SubTexture name="ExtremeDemonAnimation0023" x="0" y="0"  width="179" height="170" frameX="0" frameY="-246" frameWidth="407" frameHeight="418"/>
  <SubTexture name="ExtremeDemonAnimation0024" x="0" y="0"  width="179" height="170" frameX="0" frameY="-246" frameWidth="407" frameHeight="418"/>
  <SubTexture name="ExtremeDemonAnimation0025" x="0" y="0"  width="179" height="170" frameX="0" frameY="-246" frameWidth="407" frameHeight="418"/>
  <SubTexture name="ExtremeDemonAnimation0026" x="0" y="0"  width="179" height="170" frameX="0" frameY="-246" frameWidth="407" frameHeight="418"/>
  <SubTexture name="ExtremeDemonAnimation0027" x="0" y="0"  width="179" height="170" frameX="0" frameY="-246" frameWidth="407" frameHeight="418"/>
  <SubTexture name="ExtremeDemonAnimation0028" x="0" y="0"  width="179" height="170" frameX="0" frameY="-246" frameWidth="407" frameHeight="418"/>
  <SubTexture name="ExtremeDemonAnimation0029" x="0" y="0"  width="179" height="170" frameX="0" frameY="-246" frameWidth="407" frameHeight="418"/>
  <SubTexture name="ExtremeDemonAnimation0030" x="0" y="0"  width="179" height="170" frameX="0" frameY="-246" frameWidth="407" frameHeight="418"/>
  <SubTexture name="ExtremeDemonAnimation0031" x="0" y="0"  width="179" height="170" frameX="0" frameY="-246" frameWidth="407" frameHeight="418"/>
  <SubTexture name="ExtremeDemonAnimation0032" x="0" y="0"  width="179" height="170" frameX="0" frameY="-246" frameWidth="407" frameHeight="418"/>
  <SubTexture name="ExtremeDemonAnimation0033" x="0" y="0"  width="179" height="170" frameX="0" frameY="-246" frameWidth="407" frameHeight="418"/>
  <SubTexture name="ExtremeDemonAnimation0034" x="0" y="0"  width="179" height="170" frameX="0" frameY="-246" frameWidth="407" frameHeight="418"/>
  <SubTexture name="ExtremeDemonAnimation0035" x="0" y="0"  width="179" height="170" frameX="0" frameY="-246" frameWidth="407" frameHeight="418"/>
  <SubTexture name="ExtremeDemonAnimation0036" x="0" y="0"  width="179" height="170" frameX="0" frameY="-246" frameWidth="407" frameHeight="418"/>
  <SubTexture name="ExtremeDemonAnimation0037" x="0" y="0"  width="179" height="170" frameX="0" frameY="-246" frameWidth="407" frameHeight="418"/>
  <SubTexture name="ExtremeDemonAnimation0038" x="0" y="0"  width="179" height="170" frameX="0" frameY="-246" frameWidth="407" frameHeight="418"/>
  <SubTexture name="ExtremeDemonAnimation0039" x="0" y="0"  width="179" height="170" frameX="0" frameY="-246" frameWidth="407" frameHeight="418"/>
  <SubTexture name="ExtremeDemonAnimation0040" x="0" y="0"  width="179" height="170" frameX="0" frameY="-246" frameWidth="407" frameHeight="418"/>
  <SubTexture name="ExtremeDemonAnimation0041" x="0" y="0"  width="179" height="170" frameX="0" frameY="-246" frameWidth="407" frameHeight="418"/>
  <SubTexture name="ExtremeDemonAnimation0042" x="0" y="0"  width="179" height="170" frameX="0" frameY="-246" frameWidth="407" frameHeight="418"/>
  <SubTexture name="ExtremeDemonAnimation0043" x="0" y="0"  width="179" height="170" frameX="0" frameY="-246" frameWidth="407" frameHeight="418"/>
  <SubTexture name="ExtremeDemonAnimation0044" x="0" y="0"  width="179" height="170" frameX="0" frameY="-246" frameWidth="407" frameHeight="418"/>
  <SubTexture name="ExtremeDemonAnimation0045" x="0" y="0"  width="179" height="170" frameX="0" frameY="-246" frameWidth="407" frameHeight="418"/>
  <SubTexture name="ExtremeDemonAnimation0046" x="0" y="0"  width="179" height="170" frameX="0" frameY="-246" frameWidth="407" frameHeight="418"/>
  <SubTexture name="ExtremeDemonAnimation0047" x="0" y="0"  width="179" height="170" frameX="0" frameY="-246" frameWidth="407" frameHeight="418"/>
  <SubTexture name="ExtremeDemonAnimation0048" x="0" y="0"  width="179" height="170" frameX="0" frameY="-246" frameWidth="407" frameHeight="418"/>
  <SubTexture name="ExtremeDemonAnimation0049" x="0" y="0"  width="179" height="170" frameX="0" frameY="-246" frameWidth="407" frameHeight="418"/>
  <SubTexture name="ExtremeDemonAnimation0050" x="0" y="0"  width="179" height="170" frameX="0" frameY="-246" frameWidth="407" frameHeight="418"/>
  <SubTexture name="ExtremeDemonAnimation0051" x="0" y="0"  width="179" height="170" frameX="0" frameY="-246" frameWidth="407" frameHeight="418"/>
  <SubTexture name="ExtremeDemonAnimation0052" x="0" y="0"  width="179" height="170" frameX="0" frameY="-246" frameWidth="407" frameHeight="418"/>
  <SubTexture name="ExtremeDemonAnimation0053" x="0" y="0"  width="179" height="170" frameX="0" frameY="-246" frameWidth="407" frameHeight="418"/>
  <SubTexture name="ExtremeDemonAnimation0054" x="0" y="0"  width="179" height="170" frameX="0" frameY="-246" frameWidth="407" frameHeight="418"/>
  <SubTexture name="ExtremeDemonAnimation0055" x="0" y="0"  width="179" height="170" frameX="0" frameY="-246" frameWidth="407" frameHeight="418"/>
  <SubTexture name="ExtremeDemonAnimation0056" x="0" y="0"  width="179" height="170" frameX="0" frameY="-246" frameWidth="407" frameHeight="418"/>
  <SubTexture name="ExtremeDemonAnimation0057" x="0" y="0"  width="179" height="170" frameX="0" frameY="-246" frameWidth="407" frameHeight="418"/>
  <SubTexture name="ExtremeDemonAnimation0058" x="0" y="0"  width="179" height="170" frameX="0" frameY="-246" frameWidth="407" frameHeight="418"/>
  <SubTexture name="ExtremeDemonAnimation0059" x="0" y="0"  width="179" height="170" frameX="0" frameY="-246" frameWidth="407" frameHeight="418"/>
  <SubTexture name="ExtremeDemonAnimation0060" x="0" y="0"  width="179" height="170" frameX="0" frameY="-246" frameWidth="407" frameHeight="418"/>
  <SubTexture name="ExtremeDemonAnimation0061" x="0" y="0"  width="179" height="170" frameX="0" frameY="-246" frameWidth="407" frameHeight="418"/>
  <SubTexture name="ExtremeDemonAnimation0062" x="0" y="0"  width="179" height="170" frameX="0" frameY="-246" frameWidth="407" frameHeight="418"/>
  <SubTexture name="ExtremeDemonAnimation0063" x="0" y="0"  width="179" height="170" frameX="0" frameY="-246" frameWidth="407" frameHeight="418"/>
  <SubTexture name="ExtremeDemonAnimation0064" x="0" y="0"  width="179" height="170" frameX="0" frameY="-246" frameWidth="407" frameHeight="418"/>
  <SubTexture name="ExtremeDemonAnimation0065" x="0" y="0"  width="179" height="170" frameX="0" frameY="-246" frameWidth="407" frameHeight="418"/>
  <SubTexture name="ExtremeDemonAnimation0066" x="0" y="0"  width="179" height="170" frameX="0" frameY="-246" frameWidth="407" frameHeight="418"/>
  <SubTexture name="ExtremeDemonAnimation0067" x="0" y="0"  width="179" height="170" frameX="0" frameY="-246" frameWidth="407" frameHeight="418"/>
  <SubTexture name="ExtremeDemonAnimation0068" x="0" y="0"  width="179" height="170" frameX="0" frameY="-246" frameWidth="407" frameHeight="418"/>
  <SubTexture name="ExtremeDemonAnimation0069" x="0" y="0"  width="179" height="170" frameX="0" frameY="-246" frameWidth="407" frameHeight="418"/>
  <SubTexture name="ExtremeDemonAnimation0070" x="0" y="0"  width="179" height="170" frameX="0" frameY="-246" frameWidth="407" frameHeight="418"/>
  <SubTexture name="ExtremeDemonAnimation0071" x="0" y="0"  width="179" height="170" frameX="0" frameY="-246" frameWidth="407" frameHeight="418"/>
  <SubTexture name="ExtremeDemonAnimation0072" x="0" y="0"  width="179" height="170" frameX="0" frameY="-246" frameWidth="407" frameHeight="418"/>
  <SubTexture name="ExtremeDemonAnimation0073" x="0" y="0"  width="179" height="170" frameX="0" frameY="-246" frameWidth="407" frameHeight="418"/>
  <SubTexture name="ExtremeDemonAnimation0074" x="0" y="0"  width="179" height="170" frameX="0" frameY="-246" frameWidth="407" frameHeight="418"/>
  <SubTexture name="ExtremeDemonAnimation0075" x="0" y="0"  width="179" height="170" frameX="0" frameY="-246" frameWidth="407" frameHeight="418"/>
  <SubTexture name="ExtremeDemonAnimation0076" x="0" y="0"  width="179" height="170" frameX="0" frameY="-246" frameWidth="407" frameHeight="418"/>
  <SubTexture name="ExtremeDemonAnimation0077" x="0" y="0"  width="179" height="170" frameX="0" frameY="-246" frameWidth="407" frameHeight="418"/>
  <SubTexture name="ExtremeDemonAnimation0078" x="0" y="0"  width="179" height="170" frameX="0" frameY="-246" frameWidth="407" frameHeight="418"/>
  <SubTexture name="ExtremeDemonAnimation0079" x="0" y="0"  width="179" height="170" frameX="0" frameY="-246" frameWidth="407" frameHeight="418"/>
  <SubTexture name="ExtremeDemonAnimation0080" x="0" y="0"  width="179" height="170" frameX="0" frameY="-246" frameWidth="407" frameHeight="418"/>
  <SubTexture name="ExtremeDemonAnimation0081" x="0" y="0"  width="179" height="170" frameX="0" frameY="-246" frameWidth="407" frameHeight="418"/>
  <SubTexture name="ExtremeDemonAnimation0082" x="0" y="0"  width="179" height="170" frameX="0" frameY="-246" frameWidth="407" frameHeight="418"/>
  <SubTexture name="ExtremeDemonAnimation0083" x="0" y="0"  width="179" height="170" frameX="0" frameY="-246" frameWidth="407" frameHeight="418"/>
  <SubTexture name="ExtremeDemonAnimation0084" x="0" y="0"  width="179" height="170" frameX="0" frameY="-246" frameWidth="407" frameHeight="418"/>
  <SubTexture name="ExtremeDemonAnimation0085" x="0" y="0"  width="179" height="170" frameX="0" frameY="-246" frameWidth="407" frameHeight="418"/>
  <SubTexture name="ExtremeDemonAnimation0086" x="0" y="0"  width="179" height="170" frameX="0" frameY="-246" frameWidth="407" frameHeight="418"/>
  <SubTexture name="ExtremeDemonAnimation0087" x="0" y="0"  width="179" height="170" frameX="0" frameY="-246" frameWidth="407" frameHeight="418"/>
  <SubTexture name="ExtremeDemonAnimation0088" x="0" y="0"  width="179" height="170" frameX="0" frameY="-246" frameWidth="407" frameHeight="418"/>
  <SubTexture name="ExtremeDemonAnimation0089" x="0" y="0"  width="179" height="170" frameX="0" frameY="-246" frameWidth="407" frameHeight="418"/>
  <SubTexture name="ExtremeDemonAnimation0090" x="0" y="0"  width="179" height="170" frameX="0" frameY="-246" frameWidth="407" frameHeight="418"/>
  <SubTexture name="ExtremeDemonAnimation0091" x="0" y="0"  width="179" height="170" frameX="0" frameY="-246" frameWidth="407" frameHeight="418"/>
  <SubTexture name="ExtremeDemonAnimation0092" x="0" y="0"  width="179" height="170" frameX="0" frameY="-246" frameWidth="407" frameHeight="418"/>
  <SubTexture name="ExtremeDemonAnimation0093" x="0" y="0"  width="179" height="170" frameX="0" frameY="-246" frameWidth="407" frameHeight="418"/>
  <SubTexture name="ExtremeDemonAnimation0094" x="0" y="0"  width="179" height="170" frameX="0" frameY="-246" frameWidth="407" frameHeight="418"/>
  <SubTexture name="ExtremeDemonAnimation0095" x="0" y="0"  width="179" height="170" frameX="0" frameY="-246" frameWidth="407" frameHeight="418"/>
  <SubTexture name="ExtremeDemonAnimation0096" x="0" y="0"  width="179" height="170" frameX="0" frameY="-246" frameWidth="407" frameHeight="418"/>
  <SubTexture name="ExtremeDemonAnimation0097" x="0" y="0"  width="179" height="170" frameX="0" frameY="-246" frameWidth="407" frameHeight="418"/>
  <SubTexture name="ExtremeDemonAnimation0098" x="0" y="0"  width="179" height="170" frameX="0" frameY="-246" frameWidth="407" frameHeight="418"/>
  <SubTexture name="ExtremeDemonAnimation0099" x="0" y="0"  width="179" height="170" frameX="0" frameY="-246" frameWidth="407" frameHeight="418"/>
  <SubTexture name="ExtremeDemonAnimation0100" x="0" y="0"  width="179" height="170" frameX="0" frameY="-246" frameWidth="407" frameHeight="418"/>
  <SubTexture name="ExtremeDemonAnimation0101" x="0" y="0"  width="179" height="170" frameX="0" frameY="-246" frameWidth="407" frameHeight="418"/>
  <SubTexture name="ExtremeDemonAnimation0102" x="0" y="0"  width="179" height="170" frameX="0" frameY="-246" frameWidth="407" frameHeight="418"/>
  <SubTexture name="ExtremeDemonAnimation0103" x="0" y="0"  width="179" height="170" frameX="0" frameY="-246" frameWidth="407" frameHeight="418"/>
  <SubTexture name="ExtremeDemonAnimation0104" x="0" y="0"  width="179" height="170" frameX="0" frameY="-246" frameWidth="407" frameHeight="418"/>
  <SubTexture name="ExtremeDemonAnimation0105" x="0" y="0"  width="179" height="170" frameX="0" frameY="-246" frameWidth="407" frameHeight="418"/>
  <SubTexture name="ExtremeDemonAnimation0106" x="0" y="0"  width="179" height="170" frameX="0" frameY="-246" frameWidth="407" frameHeight="418"/>
  <SubTexture name="ExtremeDemonAnimation0107" x="0" y="0"  width="179" height="170" frameX="0" frameY="-246" frameWidth="407" frameHeight="418"/>
  <SubTexture name="ExtremeDemonAnimation0108" x="0" y="0"  width="179" height="170" frameX="0" frameY="-246" frameWidth="407" frameHeight="418"/>
  <SubTexture name="ExtremeDemonAnimation0109" x="0" y="0"  width="179" height="170" frameX="0" frameY="-246" frameWidth="407" frameHeight="418"/>
  <SubTexture name="ExtremeDemonAnimation0110" x="0" y="0"  width="179" height="170" frameX="0" frameY="-246" frameWidth="407" frameHeight="418"/>
  <SubTexture name="ExtremeDemonAnimation0111" x="0" y="0"  width="179" height="170" frameX="0" frameY="-246" frameWidth="407" frameHeight="418"/>
  <SubTexture name="ExtremeDemonAnimation0112" x="0" y="0"  width="179" height="170" frameX="0" frameY="-246" frameWidth="407" frameHeight="418"/>
  <SubTexture name="ExtremeDemonAnimation0113" x="0" y="0"  width="179" height="170" frameX="0" frameY="-246" frameWidth="407" frameHeight="418"/>
  <SubTexture name="ExtremeDemonAnimation0114" x="0" y="0"  width="179" height="170" frameX="0" frameY="-246" frameWidth="407" frameHeight="418"/>
  <SubTexture name="ExtremeDemonAnimation0115" x="0" y="0"  width="179" height="170" frameX="0" frameY="-246" frameWidth="407" frameHeight="418"/>
  <SubTexture name="ExtremeDemonAnimation0116" x="0" y="0"  width="179" height="170" frameX="0" frameY="-246" frameWidth="407" frameHeight="418"/>
  <SubTexture name="ExtremeDemonAnimation0117" x="0" y="0"  width="179" height="170" frameX="0" frameY="-246" frameWidth="407" frameHeight="418"/>
  <SubTexture name="ExtremeDemonAnimation0118" x="0" y="0"  width="179" height="170" frameX="0" frameY="-246" frameWidth="407" frameHeight="418"/>
  <SubTexture name="ExtremeDemonAnimation0119" x="0" y="0"  width="179" height="170" frameX="0" frameY="-246" frameWidth="407" frameHeight="418"/>
  <SubTexture name="ExtremeDemonAnimation0120" x="0" y="0"  width="179" height="170" frameX="0" frameY="-246" frameWidth="407" frameHeight="418"/>
  <SubTexture name="ExtremeDemonAnimation0121" x="0" y="0"  width="179" height="170" frameX="0" frameY="-246" frameWidth="407" frameHeight="418"/>
  <SubTexture name="ExtremeDemonAnimation0122" x="0" y="0"  width="179" height="170" frameX="0" frameY="-246" frameWidth="407" frameHeight="418"/>
  <SubTexture name="ExtremeDemonAnimation0123" x="0" y="0"  width="179" height="170" frameX="0" frameY="-246" frameWidth="407" frameHeight="418"/>
  <SubTexture name="ExtremeDemonAnimation0124" x="0" y="0"  width="179" height="170" frameX="0" frameY="-246" frameWidth="407" frameHeight="418"/>
  <SubTexture name="ExtremeDemonAnimation0125" x="0" y="0"  width="179" height="170" frameX="0" frameY="-246" frameWidth="407" frameHeight="418"/>
  <SubTexture name="ExtremeDemonAnimation0126" x="0" y="0"  width="179" height="170" frameX="0" frameY="-246" frameWidth="407" frameHeight="418"/>
  <SubTexture name="ExtremeDemonAnimation0127" x="0" y="0"  width="179" height="170" frameX="0" frameY="-246" frameWidth="407" frameHeight="418"/>
  <SubTexture name="ExtremeDemonAnimation0128" x="0" y="0"  width="179" height="170" frameX="0" frameY="-246" frameWidth="407" frameHeight="418"/>
  <SubTexture name="ExtremeDemonAnimation0129" x="0" y="0"  width="179" height="170" frameX="0" frameY="-246" frameWidth="407" frameHeight="418"/>
  <SubTexture name="ExtremeDemonAnimation0130" x="0" y="0"  width="179" height="170" frameX="0" frameY="-246" frameWidth="407" frameHeight="418"/>
  <SubTexture name="ExtremeDemonAnimation0131" x="0" y="0"  width="179" height="170" frameX="0" frameY="-246" frameWidth="407" frameHeight="418"/>
  <SubTexture name="ExtremeDemonAnimation0132" x="0" y="0"  width="179" height="170" frameX="0" frameY="-246" frameWidth="407" frameHeight="418"/>
  <SubTexture name="ExtremeDemonAnimation0133" x="0" y="0"  width="179" height="170" frameX="0" frameY="-246" frameWidth="407" frameHeight="418"/>
  <SubTexture name="ExtremeDemonAnimation0134" x="0" y="0"  width="179" height="170" frameX="0" frameY="-246" frameWidth="407" frameHeight="418"/>
  <SubTexture name="ExtremeDemonAnimation0135" x="0" y="0"  width="179" height="170" frameX="0" frameY="-246" frameWidth="407" frameHeight="418"/>
  <SubTexture name="ExtremeDemonAnimation0136" x="0" y="0"  width="179" height="170" frameX="0" frameY="-246" frameWidth="407" frameHeight="418"/>
  <SubTexture name="ExtremeDemonAnimation0137" x="0" y="0"  width="179" height="170" frameX="0" frameY="-246" frameWidth="407" frameHeight="418"/>
  <SubTexture name="ExtremeDemonAnimation0138" x="179" y="0"  width="182" height="170" frameX="-3" frameY="-245" frameWidth="407" frameHeight="418"/>
  <SubTexture name="ExtremeDemonAnimation0139" x="361" y="0"  width="176" height="170" frameX="-8" frameY="-241" frameWidth="407" frameHeight="418"/>
  <SubTexture name="ExtremeDemonAnimation0140" x="538" y="0"  width="174" height="170" frameX="-11" frameY="-239" frameWidth="407" frameHeight="418"/>
  <SubTexture name="ExtremeDemonAnimation0141" x="712" y="0"  width="174" height="170" frameX="-14" frameY="-236" frameWidth="407" frameHeight="418"/>
  <SubTexture name="ExtremeDemonAnimation0142" x="886" y="0"  width="172" height="170" frameX="-20" frameY="-233" frameWidth="407" frameHeight="418"/>
  <SubTexture name="ExtremeDemonAnimation0143" x="1058" y="0"  width="174" height="170" frameX="-29" frameY="-229" frameWidth="407" frameHeight="418"/>
  <SubTexture name="ExtremeDemonAnimation0144" x="1232" y="0"  width="178" height="170" frameX="-44" frameY="-222" frameWidth="407" frameHeight="418"/>
  <SubTexture name="ExtremeDemonAnimation0145" x="1411" y="0"  width="188" height="174" frameX="-56" frameY="-208" frameWidth="407" frameHeight="418"/>
  <SubTexture name="ExtremeDemonAnimation0146" x="1599" y="0"  width="213" height="174" frameX="-85" frameY="-180" frameWidth="407" frameHeight="418"/>
  <SubTexture name="ExtremeDemonAnimation0148" x="0" y="170"  width="209" height="179" frameX="-189" frameY="-98" frameWidth="407" frameHeight="418"/>
  <SubTexture name="ExtremeDemonAnimation0147" x="209" y="170"  width="217" height="181" frameX="-151" frameY="-120" frameWidth="407" frameHeight="418"/>
  <SubTexture name="ExtremeDemonAnimation0154" x="426" y="170"  width="210" height="187" frameX="-197" frameY="-29" frameWidth="407" frameHeight="418"/>
  <SubTexture name="ExtremeDemonAnimation0155" x="637" y="170"  width="210" height="187" frameX="-197" frameY="-30" frameWidth="407" frameHeight="418"/>
  <SubTexture name="ExtremeDemonAnimation0156" x="847" y="170"  width="210" height="187" frameX="-197" frameY="-31" frameWidth="407" frameHeight="418"/>
  <SubTexture name="ExtremeDemonAnimation0157" x="1058" y="170"  width="210" height="187" frameX="-197" frameY="-32" frameWidth="407" frameHeight="418"/>
  <SubTexture name="ExtremeDemonAnimation0158" x="1268" y="174"  width="210" height="187" frameX="-197" frameY="-33" frameWidth="407" frameHeight="418"/>
  <SubTexture name="ExtremeDemonAnimation0159" x="1479" y="174"  width="210" height="187" frameX="-197" frameY="-34" frameWidth="407" frameHeight="418"/>
  <SubTexture name="ExtremeDemonAnimation0160" x="1689" y="174"  width="210" height="187" frameX="-197" frameY="-35" frameWidth="407" frameHeight="418"/>
  <SubTexture name="ExtremeDemonAnimation0161" x="0" y="351"  width="210" height="187" frameX="-197" frameY="-37" frameWidth="407" frameHeight="418"/>
  <SubTexture name="ExtremeDemonAnimation0162" x="210" y="351"  width="210" height="187" frameX="-197" frameY="-39" frameWidth="407" frameHeight="418"/>
  <SubTexture name="ExtremeDemonAnimation0163" x="421" y="357"  width="210" height="187" frameX="-197" frameY="-41" frameWidth="407" frameHeight="418"/>
  <SubTexture name="ExtremeDemonAnimation0164" x="631" y="357"  width="210" height="187" frameX="-197" frameY="-44" frameWidth="407" frameHeight="418"/>
  <SubTexture name="ExtremeDemonAnimation0165" x="842" y="357"  width="210" height="187" frameX="-197" frameY="-47" frameWidth="407" frameHeight="418"/>
  <SubTexture name="ExtremeDemonAnimation0166" x="842" y="357"  width="210" height="187" frameX="-197" frameY="-47" frameWidth="407" frameHeight="418"/>
  <SubTexture name="ExtremeDemonAnimation0167" x="1052" y="357"  width="210" height="187" frameX="-197" frameY="-56" frameWidth="407" frameHeight="418"/>
  <SubTexture name="ExtremeDemonAnimation0168" x="1263" y="361"  width="210" height="187" frameX="-197" frameY="-57" frameWidth="407" frameHeight="418"/>
  <SubTexture name="ExtremeDemonAnimation0169" x="1263" y="361"  width="210" height="187" frameX="-197" frameY="-57" frameWidth="407" frameHeight="418"/>
  <SubTexture name="ExtremeDemonAnimation0170" x="1263" y="361"  width="210" height="187" frameX="-197" frameY="-57" frameWidth="407" frameHeight="418"/>
  <SubTexture name="ExtremeDemonAnimation0171" x="1263" y="361"  width="210" height="187" frameX="-197" frameY="-57" frameWidth="407" frameHeight="418"/>
  <SubTexture name="ExtremeDemonAnimation0172" x="1263" y="361"  width="210" height="187" frameX="-197" frameY="-57" frameWidth="407" frameHeight="418"/>
  <SubTexture name="ExtremeDemonAnimation0173" x="1263" y="361"  width="210" height="187" frameX="-197" frameY="-57" frameWidth="407" frameHeight="418"/>
  <SubTexture name="ExtremeDemonAnimation0174" x="1263" y="361"  width="210" height="187" frameX="-197" frameY="-57" frameWidth="407" frameHeight="418"/>
  <SubTexture name="ExtremeDemonAnimation0175" x="1263" y="361"  width="210" height="187" frameX="-197" frameY="-57" frameWidth="407" frameHeight="418"/>
  <SubTexture name="ExtremeDemonAnimation0176" x="1263" y="361"  width="210" height="187" frameX="-197" frameY="-57" frameWidth="407" frameHeight="418"/>
  <SubTexture name="ExtremeDemonAnimation0177" x="1263" y="361"  width="210" height="187" frameX="-197" frameY="-57" frameWidth="407" frameHeight="418"/>
  <SubTexture name="ExtremeDemonAnimation0178" x="1263" y="361"  width="210" height="187" frameX="-197" frameY="-57" frameWidth="407" frameHeight="418"/>
  <SubTexture name="ExtremeDemonAnimation0179" x="1263" y="361"  width="210" height="187" frameX="-197" frameY="-57" frameWidth="407" frameHeight="418"/>
  <SubTexture name="ExtremeDemonAnimation0180" x="1263" y="361"  width="210" height="187" frameX="-197" frameY="-57" frameWidth="407" frameHeight="418"/>
  <SubTexture name="ExtremeDemonAnimation0181" x="1263" y="361"  width="210" height="187" frameX="-197" frameY="-57" frameWidth="407" frameHeight="418"/>
  <SubTexture name="ExtremeDemonAnimation0182" x="1263" y="361"  width="210" height="187" frameX="-197" frameY="-57" frameWidth="407" frameHeight="418"/>
  <SubTexture name="ExtremeDemonAnimation0153" x="1473" y="361"  width="210" height="198" frameX="-197" frameY="-20" frameWidth="407" frameHeight="418"/>
  <SubTexture name="ExtremeDemonAnimation0152" x="1684" y="361"  width="210" height="210" frameX="-197" frameY="-12" frameWidth="407" frameHeight="418"/>
  <SubTexture name="ExtremeDemonUp0003" x="0" y="538"  width="414" height="199" frameX="-5" frameY="-52" frameWidth="425" frameHeight="262"/>
  <SubTexture name="ExtremeDemonUp0004" x="0" y="538"  width="414" height="199" frameX="-5" frameY="-52" frameWidth="425" frameHeight="262"/>
  <SubTexture name="ExtremeDemonDown0003" x="414" y="544"  width="338" height="202" frameX="-19" frameY="-9" frameWidth="372" frameHeight="256"/>
  <SubTexture name="ExtremeDemonDown0004" x="414" y="544"  width="338" height="202" frameX="-19" frameY="-9" frameWidth="372" frameHeight="256"/>
  <SubTexture name="ExtremeDemonIdle0006" x="752" y="544"  width="375" height="205" frameX="0" frameY="-10" frameWidth="375" frameHeight="221"/>
  <SubTexture name="ExtremeDemonIdle0007" x="752" y="544"  width="375" height="205" frameX="0" frameY="-10" frameWidth="375" frameHeight="221"/>
  <SubTexture name="ExtremeDemonAnimation0151" x="1127" y="548"  width="210" height="216" frameX="-197" frameY="-9" frameWidth="407" frameHeight="418"/>
  <SubTexture name="ExtremeDemonDown0001" x="1338" y="571"  width="359" height="206" frameX="-8" frameY="-23" frameWidth="372" frameHeight="256"/>
  <SubTexture name="ExtremeDemonDown0002" x="1338" y="571"  width="359" height="206" frameX="-8" frameY="-23" frameWidth="372" frameHeight="256"/>
  <SubTexture name="ExtremeDemonAnimation0150" x="1697" y="571"  width="210" height="230" frameX="-197" frameY="-2" frameWidth="407" frameHeight="418"/>
  <SubTexture name="ExtremeDemonIdle0016" x="0" y="738"  width="369" height="206" frameX="-1" frameY="-7" frameWidth="375" frameHeight="221"/>
  <SubTexture name="ExtremeDemonIdle0017" x="0" y="738"  width="369" height="206" frameX="-1" frameY="-7" frameWidth="375" frameHeight="221"/>
  <SubTexture name="ExtremeDemonIdle0018" x="369" y="746"  width="369" height="207" frameX="-1" frameY="-13" frameWidth="375" frameHeight="221"/>
  <SubTexture name="ExtremeDemonIdle0019" x="369" y="746"  width="369" height="207" frameX="-1" frameY="-13" frameWidth="375" frameHeight="221"/>
  <SubTexture name="ExtremeDemonIdle0004" x="738" y="750"  width="363" height="208" frameX="-1" frameY="-5" frameWidth="375" frameHeight="221"/>
  <SubTexture name="ExtremeDemonIdle0005" x="738" y="750"  width="363" height="208" frameX="-1" frameY="-5" frameWidth="375" frameHeight="221"/>
  <SubTexture name="ExtremeDemonIdle0008" x="1102" y="777"  width="363" height="208" frameX="-1" frameY="-10" frameWidth="375" frameHeight="221"/>
  <SubTexture name="ExtremeDemonIdle0009" x="1102" y="777"  width="363" height="208" frameX="-1" frameY="-10" frameWidth="375" frameHeight="221"/>
  <SubTexture name="ExtremeDemonIdle0020" x="1465" y="802"  width="363" height="208" frameX="-1" frameY="-10" frameWidth="375" frameHeight="221"/>
  <SubTexture name="ExtremeDemonIdle0021" x="1465" y="802"  width="363" height="208" frameX="-1" frameY="-10" frameWidth="375" frameHeight="221"/>
  <SubTexture name="ExtremeDemonIdle0000" x="0" y="944"  width="364" height="213" frameX="0" frameY="0" frameWidth="375" frameHeight="221"/>
  <SubTexture name="ExtremeDemonIdle0001" x="0" y="944"  width="364" height="213" frameX="0" frameY="0" frameWidth="375" frameHeight="221"/>
  <SubTexture name="ExtremeDemonIdle0010" x="364" y="954"  width="374" height="210" frameX="-1" frameY="-5" frameWidth="375" frameHeight="221"/>
  <SubTexture name="ExtremeDemonIdle0011" x="364" y="954"  width="374" height="210" frameX="-1" frameY="-5" frameWidth="375" frameHeight="221"/>
  <SubTexture name="ExtremeDemonRight0003" x="738" y="958"  width="279" height="219" frameX="-10" frameY="-22" frameWidth="344" frameHeight="251"/>
  <SubTexture name="ExtremeDemonRight0004" x="738" y="958"  width="279" height="219" frameX="-10" frameY="-22" frameWidth="344" frameHeight="251"/>
  <SubTexture name="ExtremeDemonUp0001" x="1017" y="986"  width="421" height="210" frameX="-2" frameY="-25" frameWidth="425" frameHeight="262"/>
  <SubTexture name="ExtremeDemonUp0002" x="1017" y="986"  width="421" height="210" frameX="-2" frameY="-25" frameWidth="425" frameHeight="262"/>
  <SubTexture name="ExtremeDemonIdle0014" x="1438" y="1010"  width="370" height="211" frameX="0" frameY="-3" frameWidth="375" frameHeight="221"/>
  <SubTexture name="ExtremeDemonIdle0015" x="1438" y="1010"  width="370" height="211" frameX="0" frameY="-3" frameWidth="375" frameHeight="221"/>
  <SubTexture name="ExtremeDemonIdle0012" x="0" y="1157"  width="364" height="213" frameX="0" frameY="-1" frameWidth="375" frameHeight="221"/>
  <SubTexture name="ExtremeDemonIdle0013" x="0" y="1157"  width="364" height="213" frameX="0" frameY="-1" frameWidth="375" frameHeight="221"/>
  <SubTexture name="ExtremeDemonIdle0002" x="364" y="1164"  width="374" height="211" frameX="-1" frameY="-1" frameWidth="375" frameHeight="221"/>
  <SubTexture name="ExtremeDemonIdle0003" x="364" y="1164"  width="374" height="211" frameX="-1" frameY="-1" frameWidth="375" frameHeight="221"/>
  <SubTexture name="ExtremeDemonUp0000" x="738" y="1196"  width="425" height="218" frameX="0" frameY="0" frameWidth="425" frameHeight="262"/>
  <SubTexture name="ExtremeDemonAnimation0149" x="1164" y="1196"  width="210" height="238" frameX="-197" frameY="0" frameWidth="407" frameHeight="418"/>
  <SubTexture name="ExtremeDemonDown0000" x="1374" y="1221"  width="372" height="220" frameX="0" frameY="-36" frameWidth="372" frameHeight="256"/>
  <SubTexture name="ExtremeDemonLeft0003" x="0" y="1375"  width="396" height="223" frameX="-5" frameY="-10" frameWidth="413" frameHeight="261"/>
  <SubTexture name="ExtremeDemonLeft0004" x="0" y="1375"  width="396" height="223" frameX="-5" frameY="-10" frameWidth="413" frameHeight="261"/>
  <SubTexture name="ExtremeDemonRight0001" x="396" y="1375"  width="292" height="241" frameX="-21" frameY="-10" frameWidth="344" frameHeight="251"/>
  <SubTexture name="ExtremeDemonRight0002" x="396" y="1375"  width="292" height="241" frameX="-21" frameY="-10" frameWidth="344" frameHeight="251"/>
  <SubTexture name="ExtremeDemonLeft0001" x="688" y="1415"  width="377" height="241" frameX="-4" frameY="0" frameWidth="413" frameHeight="261"/>
  <SubTexture name="ExtremeDemonLeft0002" x="688" y="1415"  width="377" height="241" frameX="-4" frameY="0" frameWidth="413" frameHeight="261"/>
  <SubTexture name="ExtremeDemonRight0000" x="1065" y="1441"  width="322" height="247" frameX="-21" frameY="0" frameWidth="344" frameHeight="251"/>
  <SubTexture name="ExtremeDemonLeft0000" x="1388" y="1441"  width="366" height="261" frameX="0" frameY="0" frameWidth="413" frameHeight="261"/>
</TextureAtlas>